track_exception/__init__.py
track_exception/core.py
track_exception-1.0.1.dist-info/LICENSE
track_exception-1.0.1.dist-info/METADATA
track_exception-1.0.1.dist-info/WHEEL
track_exception-1.0.1.dist-info/top_level.txt
track_exception-1.0.1.dist-info/RECORD
