Metadata-Version: 2.2
Name: track_exception
Version: 1.0.1
Summary: A utility to track and log website scraping exceptions in SQLite
Author: Vishvesh Jasani
Classifier: Programming Language :: Python :: 3
Classifier: Operating System :: OS Independent
Requires-Python: >=3.6
License-File: LICENSE
Dynamic: author
Dynamic: classifier
Dynamic: requires-python
Dynamic: summary
